phasor/__init__.py
phasor/alm/__init__.py
phasor/alm/beam.py
phasor/alm/beam_fit.py
phasor/alm/beam_param.py
phasor/alm/composites.py
phasor/alm/constraints.py
phasor/alm/measurements.py
phasor/alm/mounts.py
phasor/alm/mplot.py
phasor/alm/standard_attrs.py
phasor/alm/substrates.py
phasor/alm/system.py
phasor/alm/utils.py
phasor/base/__init__.py
phasor/base/autograft.py
phasor/base/bases.py
phasor/base/dictionary_keys.py
phasor/base/frequency.py
phasor/base/multi_unit_args.py
phasor/base/pint.py
phasor/base/ports.py
phasor/base/simple_units.py
phasor/base/units.py
phasor/base/utilities.py
phasor/base/visitors.py
phasor/electronics/__init__.py
phasor/electronics/elements.py
phasor/electronics/multimeter.py
phasor/electronics/noise.py
phasor/electronics/opamps.py
phasor/electronics/passive.py
phasor/electronics/ports.py
phasor/electronics/smatrix.py
phasor/electronics/sources.py
phasor/electronics/models/PDAmp.py
phasor/electronics/models/__init__.py
phasor/electronics/models/vendor_opamps.py
phasor/fitting/__init__.py
phasor/fitting/casadi/__init__.py
phasor/fitting/casadi/base.py
phasor/fitting/casadi/expressions.py
phasor/fitting/casadi/fitter.py
phasor/fitting/casadi/symbolics.py
phasor/fitting/casadi/transfer_functions.py
phasor/fitting/casadi/visitors.py
phasor/fitting/sympy/__init__.py
phasor/fitting/sympy/optical_system_sympy.py
phasor/fitting/sympy/sympy_expressionator.py
phasor/math/__init__.py
phasor/math/complex.py
phasor/math/dispatch_casadi.py
phasor/math/dispatch_defaults.py
phasor/math/dispatch_sympy.py
phasor/math/dispatched.py
phasor/math/numerics.py
phasor/math/uncert.py
phasor/math/vdispatched.py
phasor/math/key_matrix/__init__.py
phasor/math/key_matrix/autobasis.py
phasor/math/key_matrix/keyed_linear_algebra.py
phasor/math/key_matrix/keymatrix.py
phasor/math/key_matrix/keymatrix_reduce.py
phasor/math/key_matrix/keymatrix_reduce_tarjan.py
phasor/matrix/DAG_algorithm.py
phasor-1.0.0.dev3.dist-info/DESCRIPTION.rst
phasor-1.0.0.dev3.dist-info/METADATA
phasor-1.0.0.dev3.dist-info/RECORD
phasor-1.0.0.dev3.dist-info/WHEEL
phasor-1.0.0.dev3.dist-info/metadata.json
phasor-1.0.0.dev3.dist-info/top_level.txt
